mwtools/__init__.py
mwtools/mediawikitools.py
MediaWiki_Tools-0.1.1.dist-info/LICENCE
MediaWiki_Tools-0.1.1.dist-info/METADATA
MediaWiki_Tools-0.1.1.dist-info/WHEEL
MediaWiki_Tools-0.1.1.dist-info/top_level.txt
MediaWiki_Tools-0.1.1.dist-info/RECORD
