Metadata-Version: 2.1
Name: MediaWiki-Tools
Version: 0.1.1
Summary: Tools for getting data from MediaWiki websites
Home-page: https://github.com/nick-robo/MediaWiki-Tools
License: UNKNOWN
Project-URL: Bug Tracker, https://github.com/nick-robo/MediaWiki-Tools/issues
Platform: UNKNOWN
Requires-Python: >=3.8
License-File: LICENCE
Requires-Dist: requests
Requires-Dist: beautifulsoup4
Requires-Dist: pymediawiki
